pbcnet/PBCNet2.0.pth
pbcnet/__init__.py
pbcnet/cli.py
pbcnet/run.py
pbcnet/core/__init__.py
pbcnet/core/runner.py
pbcnet/model_code/__init__.py
pbcnet/model_code/Dataloader/__init__.py
pbcnet/model_code/Dataloader/dataloader.py
pbcnet/model_code/models/__init__.py
pbcnet/model_code/models/readout.py
pbcnet/model_code/models/tensornet.py
pbcnet/model_code/models/utils.py
pbcnet/model_code/models/wrappers.py
pbcnet/model_code/predict/__init__.py
pbcnet/model_code/predict/predict.py
pbcnet/model_code/utilis/__init__.py
pbcnet/model_code/utilis/function.py
pbcnet/model_code/utilis/initial.py
pbcnet/model_code/utilis/scheduler.py
pbcnet/model_code/utilis/trick.py
pbcnet/model_code/utilis/utilis.py
pbcnet-2.0.9.dist-info/METADATA
pbcnet-2.0.9.dist-info/WHEEL
pbcnet-2.0.9.dist-info/entry_points.txt
pbcnet-2.0.9.dist-info/top_level.txt
pbcnet-2.0.9.dist-info/RECORD
