Metadata-Version: 2.4
Name: pbcnet
Version: 2.0.9
Summary: PBCNet: Deep learning framework for protein-ligand binding affinity prediction
Home-page: https://github.com/yourusername/pbcnet
Author: Your Name
Author-email: Your Name <your.email@example.com>
License: MIT
Project-URL: Homepage, https://github.com/yourusername/pbcnet
Project-URL: Repository, https://github.com/yourusername/pbcnet
Project-URL: Bug Tracker, https://github.com/yourusername/pbcnet/issues
Keywords: deep learning,protein,ligand,binding affinity,drug discovery
Classifier: Development Status :: 4 - Beta
Classifier: Intended Audience :: Science/Research
Classifier: License :: OSI Approved :: MIT License
Classifier: Programming Language :: Python :: 3
Classifier: Topic :: Scientific/Engineering :: Artificial Intelligence
Requires-Python: >=3.8
Requires-Dist: torch==1.12.1
Requires-Dist: torchvision==0.13.1
Requires-Dist: torchaudio==0.12.1
Requires-Dist: dgl>=1.0.2
Requires-Dist: numpy
Requires-Dist: pandas
Requires-Dist: packaging
Requires-Dist: PyYAML
Requires-Dist: pydantic
Requires-Dist: scipy
Requires-Dist: matplotlib
Requires-Dist: rdkit-pypi
Requires-Dist: networkx
Requires-Dist: psutil
Requires-Dist: tqdm
Requires-Dist: scikit-learn
Requires-Dist: biopython
Requires-Dist: charset-normalizer==3.1.0
Requires-Dist: requests==2.28.2
Dynamic: author
Dynamic: home-page
Dynamic: requires-python
